wafcli
